txc_compressor.cp314-win32.pyd
txc_compressor-1.0.0.dist-info/licenses/LICENSE
txc_compressor-1.0.0.dist-info/METADATA
txc_compressor-1.0.0.dist-info/WHEEL
txc_compressor-1.0.0.dist-info/top_level.txt
txc_compressor-1.0.0.dist-info/RECORD
